pandopt/__init__.py
pandopt/frames.py
pandopt/groups.py
pandopt/math.py
pandopt/rolls.py
pandopt/transfcoders.py
pandopt-0.21.dist-info/LICENSE
pandopt-0.21.dist-info/METADATA
pandopt-0.21.dist-info/WHEEL
pandopt-0.21.dist-info/RECORD
