Metadata-Version: 2.1
Name: pandopt
Version: 0.21
Summary: blazzing fast ligthweight pandas wrapper
Author: remigenetaplo
Author-email: remi.genet@aplo.io
Requires-Python: >=3.12,<4.0
Classifier: Programming Language :: Python :: 3
Classifier: Programming Language :: Python :: 3.12
Requires-Dist: numba (>=0.59.0,<0.60.0)
Requires-Dist: numpy (>=1.26.4,<2.0.0)
Requires-Dist: pandas (>=2.2.0,<3.0.0)
Requires-Dist: tbb (>=2021.11.0,<2022.0.0)
